gtmkit-0.1.0.dist-info/METADATA
gtmkit-0.1.0.dist-info/WHEEL
gtmkit-0.1.0.dist-info/entry_points.txt
gtmkit-0.1.0.dist-info/licenses/LICENSE
gtmkit/__init__.py
gtmkit/gtm.py
gtmkit/metrics.py
gtmkit/plots/altair_landscapes.py
gtmkit/plots/plotly_landscapes.py
gtmkit/utils/classification.py
gtmkit/utils/density.py
gtmkit/utils/molecules.py
gtmkit/utils/regression.py
gtmkit-0.1.0.dist-info/RECORD
