Metadata-Version: 2.1
Name: GTMKit
Version: 0.1.0
Summary: A Python library for exploring chemical space using Generative Topographic Mapping.
Author-Email: "Tagir Akhmetshin, Louis Plyer, Alexey Orlov, Alexandre Varnek" <varnek@unistra.fr>
License: MIT
Requires-Python: >=3.11
Requires-Dist: numpy>=2.3.2
Requires-Dist: torch>=2.7.1
Requires-Dist: pandas>=2.3.2
Requires-Dist: altair>=5.5.0
Requires-Dist: plotly>=6.3.0
Requires-Dist: scikit-learn>=1.7.1
Requires-Dist: tqdm>=4.67.1
Requires-Dist: jupyterlab>=4.4.7
Requires-Dist: ipywidgets>=8.1.7
Requires-Dist: anywidget>=0.9.18
Requires-Dist: pyarrow>=21.0.0
